siibra_jugex/__init__.py
siibra_jugex/jugex.py
siibra_jugex-1.22.dist-info/LICENSE
siibra_jugex-1.22.dist-info/METADATA
siibra_jugex-1.22.dist-info/WHEEL
siibra_jugex-1.22.dist-info/top_level.txt
siibra_jugex-1.22.dist-info/RECORD
