Metadata-Version: 2.1
Name: siibra-jugex
Version: 1.22
Summary: siibra-jugex - Differential analysis of gene expression in brain regions using the siibra framework
Home-page: https://github.com/FZJ-INM1-BDA/siibra-jugex
Author: Big Data Analytics Group and S. Bludau, Forschungszentrum Juelich, Institute of Neuroscience and Medicine (INM-1)
Author-email: inm1-bda@fz-juelich.de
Classifier: Development Status :: 2 - Pre-Alpha
Classifier: Programming Language :: Python :: 3
Classifier: Operating System :: OS Independent
Classifier: Intended Audience :: Developers
Requires-Python: >=3.6
License-File: LICENSE
Requires-Dist: siibra >=0.4a29
Requires-Dist: statsmodels >=0.13
Requires-Dist: scipy >=1.9
